cc_python/__init__.py
cc_python/api/__init__.py
cc_python/api/client.py
cc_python/app.py
cc_python/commands/__init__.py
cc_python/commands/base.py
cc_python/commands/model.py
cc_python/commands/registry.py
cc_python/commands/session.py
cc_python/config/__init__.py
cc_python/config/settings.py
cc_python/conversation/__init__.py
cc_python/conversation/context.py
cc_python/conversation/history.py
cc_python/conversation/session.py
cc_python/models/__init__.py
cc_python/models/message.py
cc_python/permissions/__init__.py
cc_python/permissions/manager.py
cc_python/screens/__init__.py
cc_python/screens/chat.py
cc_python/tools/__init__.py
cc_python/tools/base.py
cc_python/tools/file_tools.py
cc_python/tools/git_tools.py
cc_python/tools/shell_tools.py
cc_python/widgets/__init__.py
cc_python/widgets/header.py
cc_python/widgets/input_area.py
cc_python/widgets/message_list.py
cc_python/widgets/permission_dialog.py
cc_python/widgets/status_bar.py
cc_python-0.1.0.dist-info/WHEEL
cc_python-0.1.0.dist-info/entry_points.txt
cc_python-0.1.0.dist-info/METADATA
cc_python-0.1.0.dist-info/RECORD
