Metadata-Version: 2.3
Name: cc-python
Version: 0.1.0
Summary: Claude Code style TUI application based on Python
Author: crlotwhite
Author-email: crlotwhite <crlotwhite@gmail.com>
Requires-Dist: textual[syntax]>=7.3.0
Requires-Dist: textual-dev>=1.8.0
Requires-Dist: rich>=14.2.0
Requires-Dist: typer>=0.21.1
Requires-Dist: anthropic>=0.40.0
Requires-Dist: tomli>=2.0.0
Requires-Dist: tomli-w>=1.0.0
Requires-Dist: tiktoken>=0.8.0
Requires-Dist: gitpython>=3.1.0
Requires-Dist: aiofiles>=24.0.0
Requires-Python: >=3.12
